<xml xmlns="https://developers.google.com/blockly/xml"><block type="start_block" id="%Z6q]02lY+g4Mh+)5,2P" deletable="false" x="200" y="10"><next><block type="move_block" id="`m0sNJ`G7+i^7zbrzrOP"><field name="?box">box_small</field><field name="?from">box_medium</field><field name="?to">location_ii</field><field name="?robot">fetch</field><data>?box ?from ?robot ?to</data><next><block type="move_block" id="Z1S_N{Qn$X+$@Sv,p:!d"><field name="?box">box_small</field><field name="?from">location_ii</field><field name="?to">box_small</field><field name="?robot">fetch</field><data>?box ?from ?robot ?to</data></block></next></block></next></block></xml>